chmod_reset/__init__.py
chmod_reset/__main__.py
chmod_reset/chmod_reset.py
chmod_reset-0.1.0.dist-info/METADATA
chmod_reset-0.1.0.dist-info/RECORD
chmod_reset-0.1.0.dist-info/WHEEL
chmod_reset-0.1.0.dist-info/entry_points.txt
chmod_reset-0.1.0.dist-info/pbr.json
chmod_reset-0.1.0.dist-info/top_level.txt
