Metadata-Version: 2.1
Name: chmod-reset
Version: 0.1.0
Summary: Python package to reset right acces on all files, folders and sub-files and folders
Home-page: http://github.com/seignovert/python-chmod-reset
Author: Benoit Seignovert
Author-email: python@seignovert.fr
License: MIT
Keywords: chmod
Platform: UNKNOWN
Classifier: Development Status :: 3 - Alpha
Classifier: Natural Language :: English
Classifier: License :: OSI Approved :: MIT License
Classifier: Programming Language :: Python
Classifier: Programming Language :: Python :: 2.7
Classifier: Programming Language :: Python :: 3.6
Classifier: Topic :: System
Classifier: Topic :: System :: System Shells
Requires-Dist: argparse
